{"timestamp": 1741892885.281367, "expiry": 86400, "data": [{"title": "", "authors": null, "abstract": null, "doi": null, "year": null, "url": "https://ui.adsabs.harvard.edu/abs//abstract", "source": "ads", "rank": 1}, {"title": "", "authors": null, "abstract": null, "doi": null, "year": null, "url": "https://ui.adsabs.harvard.edu/abs//abstract", "source": "ads", "rank": 2}, {"title": "", "authors": null, "abstract": null, "doi": null, "year": null, "url": "https://ui.adsabs.harvard.edu/abs//abstract", "source": "ads", "rank": 3}, {"title": "", "authors": null, "abstract": null, "doi": null, "year": null, "url": "https://ui.adsabs.harvard.edu/abs//abstract", "source": "ads", "rank": 4}, {"title": "", "authors": null, "abstract": null, "doi": null, "year": null, "url": "https://ui.adsabs.harvard.edu/abs//abstract", "source": "ads", "rank": 5}, {"title": "", "authors": null, "abstract": null, "doi": null, "year": null, "url": "https://ui.adsabs.harvard.edu/abs//abstract", "source": "ads", "rank": 6}, {"title": "", "authors": null, "abstract": null, "doi": null, "year": null, "url": "https://ui.adsabs.harvard.edu/abs//abstract", "source": "ads", "rank": 7}, {"title": "", "authors": null, "abstract": null, "doi": null, "year": null, "url": "https://ui.adsabs.harvard.edu/abs//abstract", "source": "ads", "rank": 8}, {"title": "", "authors": null, "abstract": null, "doi": null, "year": null, "url": "https://ui.adsabs.harvard.edu/abs//abstract", "source": "ads", "rank": 9}, {"title": "", "authors": null, "abstract": null, "doi": null, "year": null, "url": "https://ui.adsabs.harvard.edu/abs//abstract", "source": "ads", "rank": 10}, {"title": "", "authors": null, "abstract": null, "doi": null, "year": null, "url": "https://ui.adsabs.harvard.edu/abs//abstract", "source": "ads", "rank": 11}, {"title": "", "authors": null, "abstract": null, "doi": null, "year": null, "url": "https://ui.adsabs.harvard.edu/abs//abstract", "source": "ads", "rank": 12}, {"title": "", "authors": null, "abstract": null, "doi": null, "year": null, "url": "https://ui.adsabs.harvard.edu/abs//abstract", "source": "ads", "rank": 13}, {"title": "", "authors": null, "abstract": null, "doi": null, "year": null, "url": "https://ui.adsabs.harvard.edu/abs//abstract", "source": "ads", "rank": 14}, {"title": "", "authors": null, "abstract": null, "doi": null, "year": null, "url": "https://ui.adsabs.harvard.edu/abs//abstract", "source": "ads", "rank": 15}, {"title": "", "authors": null, "abstract": null, "doi": null, "year": null, "url": "https://ui.adsabs.harvard.edu/abs//abstract", "source": "ads", "rank": 16}, {"title": "", "authors": null, "abstract": null, "doi": null, "year": null, "url": "https://ui.adsabs.harvard.edu/abs//abstract", "source": "ads", "rank": 17}, {"title": "", "authors": null, "abstract": null, "doi": null, "year": null, "url": "https://ui.adsabs.harvard.edu/abs//abstract", "source": "ads", "rank": 18}, {"title": "", "authors": null, "abstract": null, "doi": null, "year": null, "url": "https://ui.adsabs.harvard.edu/abs//abstract", "source": "ads", "rank": 19}, {"title": "", "authors": null, "abstract": null, "doi": null, "year": null, "url": "https://ui.adsabs.harvard.edu/abs//abstract", "source": "ads", "rank": 20}]}